microbex/__init__.py
microbex/microbex.py
microbex/sample_data/__init__.py
microbex/sample_data/sample_annotation.pkl
microbex/sample_data/sample_data.csv
microbex/tests/__init__.py
microbex/tests/test_microbex.py
microbex/utils/__init__.py
microbex/utils/ohdsi_mapping.py
microbex/utils/regex_blocks.py
microbex-0.0.3.dist-info/LICENSE.txt
microbex-0.0.3.dist-info/METADATA
microbex-0.0.3.dist-info/WHEEL
microbex-0.0.3.dist-info/top_level.txt
microbex-0.0.3.dist-info/RECORD
