Metadata-Version: 2.1
Name: microbex
Version: 0.0.3
Summary: a rule-based clinical concept extraction tool to capture microorganisms and estimate infection status on semi-structured microbiology culture reports.
Home-page: https://github.com/geickelb/microbex
Author: Garrett Eickelberg
Author-email: garrett.eickelberg@northwestern.edu
License: UNKNOWN
Platform: UNKNOWN
Classifier: Programming Language :: Python :: 3
Classifier: License :: OSI Approved :: MIT License
Classifier: Operating System :: OS Independent
Requires-Python: >=3.6.8
License-File: LICENSE.txt
